resotoappbundler/__init__.py
resotoappbundler/__main__.py
resotoappbundler/bundler.py
resotoappbundler/runner.py
resotoappbundler-0.4.0.dist-info/LICENSE
resotoappbundler-0.4.0.dist-info/METADATA
resotoappbundler-0.4.0.dist-info/WHEEL
resotoappbundler-0.4.0.dist-info/entry_points.txt
resotoappbundler-0.4.0.dist-info/top_level.txt
resotoappbundler-0.4.0.dist-info/RECORD
