Metadata-Version: 2.1
Name: resotoappbundler
Version: 0.4.0
Summary: Exports Resoto metrics in Prometheus format.
Home-page: https://github.com/someengineering/resoto-apps/tree/main/resotoappbundler
License: Apache 2.0
Keywords: cloud security
Classifier: Development Status :: 4 - Beta
Classifier: Intended Audience :: System Administrators
Classifier: Intended Audience :: Information Technology
Classifier: License :: OSI Approved :: Apache Software License
Classifier: Programming Language :: Python :: 3.9
Classifier: Operating System :: POSIX :: Linux
Classifier: Operating System :: Unix
Classifier: Environment :: Console
Classifier: Natural Language :: English
Classifier: Topic :: Security
Classifier: Topic :: Utilities
License-File: LICENSE
Requires-Dist: PyYAML (==6.0)
Requires-Dist: Jinja2 (==3.1.2)
Requires-Dist: resotolib (>=3.5.2)
